loop/__init__.py
loop/base_evaluator.py
loop/evaluators.py
loop/io_mixins.py
loop/loop_evaluator.py
loop/loop_parser.py
loop_calc-0.1.2.dist-info/LICENSE
loop_calc-0.1.2.dist-info/METADATA
loop_calc-0.1.2.dist-info/WHEEL
loop_calc-0.1.2.dist-info/entry_points.txt
loop_calc-0.1.2.dist-info/top_level.txt
loop_calc-0.1.2.dist-info/RECORD
