Metadata-Version: 2.1
Name: loop-calc
Version: 0.1.2
Summary: This program evaluates loop programs as described in the lecture 'Grundlagen der theoretischen Informatik 2'.
Home-page: https://github.com/fin-ger/loop-calc
Author: Fin Christensen
Author-email: christensen.fin@gmail.com
License: UNKNOWN
Platform: UNKNOWN
Classifier: Programming Language :: Python :: 3
Classifier: License :: OSI Approved :: GNU General Public License v2 or later (GPLv2+)
Classifier: Operating System :: OS Independent
Requires-Dist: pyparsing (>=2)
